libtorrent-stubs/__init__.pyi
libtorrent-stubs/py.typed
libtorrent_stubs-0.0.1.dist-info/WHEEL
libtorrent_stubs-0.0.1.dist-info/METADATA
libtorrent_stubs-0.0.1.dist-info/RECORD
